{
  "lastUpdated": "2026-04-29T05:51:16.907561-06:00",
  "leaderboard": [
    {
      "name": "Sean",
      "score": 2550.0,
      "zones": {
        "Z1": 20.308276929956083,
        "Z2": 13.593811708608778,
        "Z3": 25.63718018262889,
        "Z4": 15.04655744585697,
        "Z5": 0.14594140950444512
      },
      "last_7": {
        "Thu (04/23)": 48.5,
        "Fri (04/24)": 0.0,
        "Sat (04/25)": 50,
        "Sun (04/26)": 0,
        "Mon (04/27)": 0,
        "Tue (04/28)": 0,
        "Wed (04/29)": 0,
        "PTO remaining": 366.0
      },
      "sports": {
        "Run": 31.0,
        "Walk": 4.0,
        "WeightTraining": 6.0,
        "Racquetball": 8.0,
        "Hike": 5.0,
        "Soccer": 1.0,
        "Swim": 1.0,
        "Ride": 1.0
      },
      "march": 611.0166666666667
    },
    {
      "name": "Robyn",
      "score": 2600.0,
      "zones": {
        "Z1": 42.19532677364553,
        "Z2": 30.789645307949208,
        "Z3": 14.528690940373451,
        "Z4": 4.081289044357794,
        "Z5": 0.8814557213018185
      },
      "last_7": {
        "Thu (04/23)": 50,
        "Fri (04/24)": 50,
        "Sat (04/25)": 0,
        "Sun (04/26)": 29.6,
        "Mon (04/27)": 0,
        "Tue (04/28)": 50,
        "Wed (04/29)": 0,
        "PTO remaining": 727.2
      },
      "sports": {
        "WeightTraining": 70.0,
        "Walk": 100.0,
        "Workout": 7.0,
        "Hike": 2.0,
        "Pickleball": 2.0,
        "Rowing": 1.0
      },
      "march": 972.7166666666666
    },
    {
      "name": "Joseph",
      "score": 2678.2,
      "zones": {
        "Z1": 67.528230374829,
        "Z2": 12.149552745791956,
        "Z3": 6.7962135911992645,
        "Z4": 2.4629741648595638,
        "Z5": 0.41941050233829014
      },
      "last_7": {
        "Thu (04/23)": 36.9,
        "Fri (04/24)": 34.4,
        "Sat (04/25)": 30.1,
        "Sun (04/26)": 0,
        "Mon (04/27)": 36.4,
        "Tue (04/28)": 44.0,
        "Wed (04/29)": 47.9,
        "PTO remaining": 510.7
      },
      "sports": {
        "WeightTraining": 79.0,
        "Walk": 9.0,
        "Ride": 4.0,
        "Workout": 1.0
      },
      "march": 730.8833333333333
    },
    {
      "name": "Nelson",
      "score": 2568.0,
      "zones": {
        "Z1": 55.6047293918158,
        "Z2": 11.20956188255848,
        "Z3": 7.152338305821218,
        "Z4": 7.181974298352792,
        "Z5": 3.8883242857861844
      },
      "last_7": {
        "Thu (04/23)": 25.0,
        "Fri (04/24)": 0,
        "Sat (04/25)": 48.5,
        "Sun (04/26)": 50,
        "Mon (04/27)": 0,
        "Tue (04/28)": 18.0,
        "Wed (04/29)": 0,
        "PTO remaining": 342.2
      },
      "sports": {
        "Walk": 52.0,
        "Ride": 18.0,
        "Workout": 9.0,
        "Pickleball": 1.0,
        "Run": 2.0,
        "HighIntensityIntervalTraining": 4.0,
        "Basketball": 1.0,
        "WeightTraining": 1.0,
        "Dance": 1.0
      },
      "march": 564.3166666666666
    },
    {
      "name": "Morgan",
      "score": 2600.0,
      "zones": {
        "Z1": 71.11875255304999,
        "Z2": 16.316255700600358,
        "Z3": 6.904368593799217,
        "Z4": 0.4994263229010712,
        "Z5": 0.0
      },
      "last_7": {
        "Thu (04/23)": 50,
        "Fri (04/24)": 50,
        "Sat (04/25)": 50,
        "Sun (04/26)": 0,
        "Mon (04/27)": 0,
        "Tue (04/28)": 50,
        "Wed (04/29)": 0,
        "PTO remaining": 750
      },
      "sports": {
        "WeightTraining": 39.0,
        "Walk": 65.0,
        "Ride": 2.0,
        "Hike": 1.0
      },
      "march": 1545.6833333333334
    },
    {
      "name": "Gabby",
      "score": 2571.4,
      "zones": {
        "Z1": 65.25274310088258,
        "Z2": 14.376863990670016,
        "Z3": 8.624744319218621,
        "Z4": 6.747227077302721,
        "Z5": 1.2611334377137395
      },
      "last_7": {
        "Thu (04/23)": 50,
        "Fri (04/24)": 14.8,
        "Sat (04/25)": 27.7,
        "Sun (04/26)": 0,
        "Mon (04/27)": 21.4,
        "Tue (04/28)": 0,
        "Wed (04/29)": 0,
        "PTO remaining": 1.3
      },
      "sports": {
        "Walk": 12.0,
        "Ride": 20.0,
        "Run": 27.0,
        "WeightTraining": 21.0,
        "Hike": 5.0,
        "Volleyball": 1.0,
        "Workout": 2.0
      },
      "march": 391.46666666666664
    },
    {
      "name": "Kailey",
      "score": 2581.4,
      "zones": {
        "Z1": 80.12229226608902,
        "Z2": 5.573949268188342,
        "Z3": 1.2782954221724516,
        "Z4": 0.6834273428761469,
        "Z5": 0.002827766403872909
      },
      "last_7": {
        "Thu (04/23)": 0,
        "Fri (04/24)": 34.0,
        "Sat (04/25)": 14.4,
        "Sun (04/26)": 33.2,
        "Mon (04/27)": 0,
        "Tue (04/28)": 31.4,
        "Wed (04/29)": 0,
        "PTO remaining": 330.8
      },
      "sports": {
        "Elliptical": 21.0,
        "Walk": 72.0,
        "Run": 7.0,
        "Pickleball": 1.0
      },
      "march": 642.4499999999998
    },
    {
      "name": "Glenn",
      "score": 2591.8,
      "zones": {
        "Z1": 51.12355894780251,
        "Z2": 6.8500406811913885,
        "Z3": 2.6053203583955287,
        "Z4": 0.7365233437108112,
        "Z5": 0.09466715972016031
      },
      "last_7": {
        "Thu (04/23)": 0,
        "Fri (04/24)": 50,
        "Sat (04/25)": 0,
        "Sun (04/26)": 33.6,
        "Mon (04/27)": 14.9,
        "Tue (04/28)": 26.9,
        "Wed (04/29)": 0,
        "PTO remaining": 527.0
      },
      "sports": {
        "WeightTraining": 17.0,
        "Walk": 57.0,
        "Ride": 12.0,
        "Run": 27.0
      },
      "march": 664.1833333333333
    },
    {
      "name": "Darlene",
      "score": 2565.2,
      "zones": {
        "Z1": 88.40902585751078,
        "Z2": 9.608553672784447,
        "Z3": 1.4043710917918664,
        "Z4": 0.3701132057103164,
        "Z5": 0.0
      },
      "last_7": {
        "Thu (04/23)": 6.1,
        "Fri (04/24)": 0,
        "Sat (04/25)": 0,
        "Sun (04/26)": 50,
        "Mon (04/27)": 0,
        "Tue (04/28)": 15.2,
        "Wed (04/29)": 0,
        "PTO remaining": 95.7
      },
      "sports": {
        "Workout": 75.0,
        "Walk": 2.0,
        "Yoga": 1.0
      },
      "march": 739.7833333333333
    },
    {
      "name": "Brad",
      "score": 2648.3,
      "zones": {
        "Z1": 51.34198490624699,
        "Z2": 6.27866647548606,
        "Z3": 10.796460026358044,
        "Z4": 1.7525059115800907,
        "Z5": 0.24328970280877846
      },
      "last_7": {
        "Thu (04/23)": 47.7,
        "Fri (04/24)": 50,
        "Sat (04/25)": 0,
        "Sun (04/26)": 0,
        "Mon (04/27)": 48.3,
        "Tue (04/28)": 50,
        "Wed (04/29)": 0,
        "PTO remaining": 750
      },
      "sports": {
        "WeightTraining": 49.0,
        "Run": 40.0,
        "Walk": 14.0,
        "Ride": 3.0
      },
      "march": 1206.3166666666668
    },
    {
      "name": "Kevin",
      "score": 2127.8,
      "zones": {
        "Z1": 84.71639286925354,
        "Z2": 10.032926180391232,
        "Z3": 4.4370316527271925,
        "Z4": 0.40601486846692836,
        "Z5": 0.0
      },
      "last_7": {
        "Thu (04/23)": 23.8,
        "Fri (04/24)": 0,
        "Sat (04/25)": 1.6,
        "Sun (04/26)": 0,
        "Mon (04/27)": 0,
        "Tue (04/28)": 0,
        "Wed (04/29)": 0,
        "PTO remaining": 0
      },
      "sports": {
        "Ride": 22.0,
        "Walk": 44.0,
        "Workout": 1.0
      },
      "march": 602.1166666666666
    },
    {
      "name": "Matthew",
      "score": 1417.2,
      "zones": {
        "Z1": 69.62645940029643,
        "Z2": 13.473537758173165,
        "Z3": 1.5766916503326331,
        "Z4": 0.2542988617098571,
        "Z5": 0.0030273674013078225
      },
      "last_7": {
        "Thu (04/23)": 0,
        "Fri (04/24)": 0,
        "Sat (04/25)": 0,
        "Sun (04/26)": 0,
        "Mon (04/27)": 0,
        "Tue (04/28)": 0,
        "Wed (04/29)": 0,
        "PTO remaining": 0
      },
      "sports": {
        "Walk": 45.0,
        "Workout": 11.0,
        "Elliptical": 1.0
      },
      "march": 546.95
    },
    {
      "name": "Tiffanie",
      "score": 1384.0,
      "zones": {
        "Z1": 77.13836225476226,
        "Z2": 10.185446166977709,
        "Z3": 0.5426135036870523,
        "Z4": 0.3753493446660918,
        "Z5": 0.0
      },
      "last_7": {
        "Thu (04/23)": 0,
        "Fri (04/24)": 0,
        "Sat (04/25)": 0,
        "Sun (04/26)": 0,
        "Mon (04/27)": 29.7,
        "Tue (04/28)": 0,
        "Wed (04/29)": 0,
        "PTO remaining": 0
      },
      "sports": {
        "Walk": 44.0
      },
      "march": 334.44999999999993
    },
    {
      "name": "Sarah",
      "score": 1015.3,
      "zones": {
        "Z1": 16.007933239462442,
        "Z2": 1.5908382276047934,
        "Z3": 0.22008710350323005,
        "Z4": 0.08949873530408907,
        "Z5": 0.031292672175462874
      },
      "last_7": {
        "Thu (04/23)": 0,
        "Fri (04/24)": 0.0,
        "Sat (04/25)": 0,
        "Sun (04/26)": 0,
        "Mon (04/27)": 0.0,
        "Tue (04/28)": 0,
        "Wed (04/29)": 0.0,
        "PTO remaining": 0
      },
      "sports": {
        "WeightTraining": 75.0
      },
      "march": 16.533333333333335
    }
  ],
  "total_score": 31898.6,
  "potential": 107014.5
}