{
  "lastUpdated": "2026-01-01T07:00:47.111127-07:00",
  "leaderboard": [
    {
      "name": "Sean",
      "score": 0,
      "zones": {
        "Z1": 0,
        "Z2": 0,
        "Z3": 0,
        "Z4": 0,
        "Z5": 0
      },
      "last_7": {
        "Fri (12/26)": 0,
        "Sat (12/27)": 0,
        "Sun (12/28)": 0,
        "Mon (12/29)": 0,
        "Tue (12/30)": 0,
        "Wed (12/31)": 0,
        "Thu (01/01)": 0,
        "PTO remaining": 750
      },
      "sports": {}
    },
    {
      "name": "Robyn",
      "score": 0,
      "zones": {
        "Z1": 0,
        "Z2": 0,
        "Z3": 0,
        "Z4": 0,
        "Z5": 0
      },
      "last_7": {
        "Fri (12/26)": 0,
        "Sat (12/27)": 0,
        "Sun (12/28)": 0,
        "Mon (12/29)": 0,
        "Tue (12/30)": 0,
        "Wed (12/31)": 0,
        "Thu (01/01)": 0,
        "PTO remaining": 750
      },
      "sports": {}
    },
    {
      "name": "Joseph",
      "score": 0,
      "zones": {
        "Z1": 0,
        "Z2": 0,
        "Z3": 0,
        "Z4": 0,
        "Z5": 0
      },
      "last_7": {
        "Fri (12/26)": 0,
        "Sat (12/27)": 0,
        "Sun (12/28)": 0,
        "Mon (12/29)": 0,
        "Tue (12/30)": 0,
        "Wed (12/31)": 0,
        "Thu (01/01)": 0,
        "PTO remaining": 750
      },
      "sports": {}
    },
    {
      "name": "Nelson",
      "score": 0,
      "zones": {
        "Z1": 0,
        "Z2": 0,
        "Z3": 0,
        "Z4": 0,
        "Z5": 0
      },
      "last_7": {
        "Fri (12/26)": 0,
        "Sat (12/27)": 0,
        "Sun (12/28)": 0,
        "Mon (12/29)": 0,
        "Tue (12/30)": 0,
        "Wed (12/31)": 0,
        "Thu (01/01)": 0,
        "PTO remaining": 750
      },
      "sports": {}
    },
    {
      "name": "Morgan",
      "score": 0,
      "zones": {
        "Z1": 0,
        "Z2": 0,
        "Z3": 0,
        "Z4": 0,
        "Z5": 0
      },
      "last_7": {
        "Fri (12/26)": 0,
        "Sat (12/27)": 0,
        "Sun (12/28)": 0,
        "Mon (12/29)": 0,
        "Tue (12/30)": 0,
        "Wed (12/31)": 0,
        "Thu (01/01)": 0,
        "PTO remaining": 750
      },
      "sports": {}
    },
    {
      "name": "Gabby",
      "score": 0,
      "zones": {
        "Z1": 0,
        "Z2": 0,
        "Z3": 0,
        "Z4": 0,
        "Z5": 0
      },
      "last_7": {
        "Fri (12/26)": 0,
        "Sat (12/27)": 0,
        "Sun (12/28)": 0,
        "Mon (12/29)": 0,
        "Tue (12/30)": 0,
        "Wed (12/31)": 0,
        "Thu (01/01)": 0,
        "PTO remaining": 750
      },
      "sports": {}
    },
    {
      "name": "Kailey",
      "score": 0,
      "zones": {
        "Z1": 0,
        "Z2": 0,
        "Z3": 0,
        "Z4": 0,
        "Z5": 0
      },
      "last_7": {
        "Fri (12/26)": 0,
        "Sat (12/27)": 0,
        "Sun (12/28)": 0,
        "Mon (12/29)": 0,
        "Tue (12/30)": 0,
        "Wed (12/31)": 0,
        "Thu (01/01)": 0,
        "PTO remaining": 750
      },
      "sports": {}
    },
    {
      "name": "Glenn",
      "score": 0,
      "zones": {
        "Z1": 0,
        "Z2": 0,
        "Z3": 0,
        "Z4": 0,
        "Z5": 0
      },
      "last_7": {
        "Fri (12/26)": 0,
        "Sat (12/27)": 0,
        "Sun (12/28)": 0,
        "Mon (12/29)": 0,
        "Tue (12/30)": 0,
        "Wed (12/31)": 0,
        "Thu (01/01)": 0,
        "PTO remaining": 750
      },
      "sports": {}
    },
    {
      "name": "Darlene",
      "score": 0,
      "zones": {
        "Z1": 0,
        "Z2": 0,
        "Z3": 0,
        "Z4": 0,
        "Z5": 0
      },
      "last_7": {
        "Fri (12/26)": 0,
        "Sat (12/27)": 0,
        "Sun (12/28)": 0,
        "Mon (12/29)": 0,
        "Tue (12/30)": 0,
        "Wed (12/31)": 0,
        "Thu (01/01)": 0,
        "PTO remaining": 750
      },
      "sports": {}
    },
    {
      "name": "Brad",
      "score": 0,
      "zones": {
        "Z1": 10.290135396518375,
        "Z2": 64.10058027079305,
        "Z3": 25.60928433268859,
        "Z4": 0.0,
        "Z5": 0.0
      },
      "last_7": {
        "Fri (12/26)": 0,
        "Sat (12/27)": 0,
        "Sun (12/28)": 0,
        "Mon (12/29)": 0,
        "Tue (12/30)": 0,
        "Wed (12/31)": 43.1,
        "Thu (01/01)": 0,
        "PTO remaining": 750
      },
      "sports": {
        "Run": 1.0
      }
    },
    {
      "name": "Kevin",
      "score": 0,
      "zones": {
        "Z1": 0,
        "Z2": 0,
        "Z3": 0,
        "Z4": 0,
        "Z5": 0
      },
      "last_7": {
        "Fri (12/26)": 0,
        "Sat (12/27)": 0,
        "Sun (12/28)": 0,
        "Mon (12/29)": 0,
        "Tue (12/30)": 0,
        "Wed (12/31)": 0,
        "Thu (01/01)": 0,
        "PTO remaining": 750
      },
      "sports": {}
    },
    {
      "name": "Matthew",
      "score": 0,
      "zones": {
        "Z1": 0,
        "Z2": 0,
        "Z3": 0,
        "Z4": 0,
        "Z5": 0
      },
      "last_7": {
        "Fri (12/26)": 0,
        "Sat (12/27)": 0,
        "Sun (12/28)": 0,
        "Mon (12/29)": 0,
        "Tue (12/30)": 0,
        "Wed (12/31)": 0,
        "Thu (01/01)": 0,
        "PTO remaining": 750
      },
      "sports": {}
    },
    {
      "name": "Tiffanie",
      "score": 0,
      "zones": {
        "Z1": 0,
        "Z2": 0,
        "Z3": 0,
        "Z4": 0,
        "Z5": 0
      },
      "last_7": {
        "Fri (12/26)": 0,
        "Sat (12/27)": 0,
        "Sun (12/28)": 0,
        "Mon (12/29)": 0,
        "Tue (12/30)": 0,
        "Wed (12/31)": 0,
        "Thu (01/01)": 0,
        "PTO remaining": 750
      },
      "sports": {}
    },
    {
      "name": "S",
      "score": 0,
      "zones": {
        "Z1": 0,
        "Z2": 0,
        "Z3": 0,
        "Z4": 0,
        "Z5": 0
      },
      "last_7": {
        "Fri (12/26)": 0,
        "Sat (12/27)": 0,
        "Sun (12/28)": 0,
        "Mon (12/29)": 0,
        "Tue (12/30)": 0,
        "Wed (12/31)": 0,
        "Thu (01/01)": 0,
        "PTO remaining": 750
      },
      "sports": {}
    }
  ]
}