{
  "lastUpdated": "2025-12-26T12:33:42.245093-07:00",
  "leaderboard": [
    {
      "name": "Sean",
      "score": 1073.9,
      "zones": {
        "Z1": 25.09248214218155,
        "Z2": 19.274434921804005,
        "Z3": 30.176634730333095,
        "Z4": 19.134084169836296,
        "Z5": 0.0
      },
      "last_7": {
        "Sat (12/20)": 50,
        "Sun (12/21)": 0,
        "Mon (12/22)": 0,
        "Tue (12/23)": 0,
        "Wed (12/24)": 50,
        "Thu (12/25)": 0,
        "Fri (12/26)": 50,
        "PTO remaining": 0
      },
      "sports": {
        "Run": 5.0,
        "Ride": 3.0,
        "Workout": 2.0,
        "Racquetball": 1.0
      }
    },
    {
      "name": "Robyn",
      "score": 1115.6,
      "zones": {
        "Z1": 46.04123656659594,
        "Z2": 30.82350619764779,
        "Z3": 11.127117418863563,
        "Z4": 8.655465284913232,
        "Z5": 3.3526745319792504
      },
      "last_7": {
        "Sat (12/20)": 0,
        "Sun (12/21)": 0,
        "Mon (12/22)": 0,
        "Tue (12/23)": 0,
        "Wed (12/24)": 0,
        "Thu (12/25)": 0,
        "Fri (12/26)": 0,
        "PTO remaining": 0
      },
      "sports": {
        "Workout": 1.0,
        "WeightTraining": 15.0,
        "Walk": 4.0
      }
    },
    {
      "name": "Joseph",
      "score": 900,
      "zones": {
        "Z1": 40.83023030726089,
        "Z2": 43.84788974778825,
        "Z3": 10.052871813134802,
        "Z4": 4.029920788646602,
        "Z5": 1.2390873431694553
      },
      "last_7": {
        "Sat (12/20)": 31.8,
        "Sun (12/21)": 0,
        "Mon (12/22)": 35.6,
        "Tue (12/23)": 39.2,
        "Wed (12/24)": 37.7,
        "Thu (12/25)": 0,
        "Fri (12/26)": 40.8,
        "PTO remaining": 0
      },
      "sports": {
        "WeightTraining": 9.0
      }
    },
    {
      "name": "Nelson",
      "score": 648.9,
      "zones": {
        "Z1": 36.003454180735964,
        "Z2": 63.99654581926342,
        "Z3": 0.0,
        "Z4": 0.0,
        "Z5": 0.0
      },
      "last_7": {
        "Sat (12/20)": 0,
        "Sun (12/21)": 0,
        "Mon (12/22)": 0,
        "Tue (12/23)": 0,
        "Wed (12/24)": 0,
        "Thu (12/25)": 17.8,
        "Fri (12/26)": 0,
        "PTO remaining": 0
      },
      "sports": {
        "Walk": 2.0
      }
    },
    {
      "name": "Morgan",
      "score": 900,
      "zones": {
        "Z1": 24.33492773265489,
        "Z2": 63.22509359445314,
        "Z3": 11.136733924243433,
        "Z4": 1.2753953438416399,
        "Z5": 0.027849404807044603
      },
      "last_7": {
        "Sat (12/20)": 0,
        "Sun (12/21)": 0,
        "Mon (12/22)": 33.6,
        "Tue (12/23)": 50,
        "Wed (12/24)": 41.3,
        "Thu (12/25)": 37.9,
        "Fri (12/26)": 0,
        "PTO remaining": 0
      },
      "sports": {
        "WeightTraining": 2.0,
        "HighIntensityIntervalTraining": 1.0,
        "Yoga": 1.0,
        "Walk": 9.0
      }
    },
    {
      "name": "Gabby",
      "score": 717.8,
      "zones": {
        "Z1": 32.821029161161,
        "Z2": 34.502177141887465,
        "Z3": 5.649428974340849,
        "Z4": 0.04675530432805181,
        "Z5": 0.0
      },
      "last_7": {
        "Sat (12/20)": 50,
        "Sun (12/21)": 0,
        "Mon (12/22)": 50,
        "Tue (12/23)": 0,
        "Wed (12/24)": 0,
        "Thu (12/25)": 0,
        "Fri (12/26)": 0,
        "PTO remaining": 0
      },
      "sports": {
        "Pickleball": 1.0,
        "WeightTraining": 2.0,
        "Ride": 2.0
      }
    },
    {
      "name": "Kailey",
      "score": 600,
      "zones": {
        "Z1": 0,
        "Z2": 0,
        "Z3": 0,
        "Z4": 0,
        "Z5": 0
      },
      "last_7": {
        "Sat (12/20)": 0,
        "Sun (12/21)": 0,
        "Mon (12/22)": 0,
        "Tue (12/23)": 0,
        "Wed (12/24)": 0,
        "Thu (12/25)": 0,
        "Fri (12/26)": 0,
        "PTO remaining": 0
      },
      "sports": {}
    },
    {
      "name": "Glenn",
      "score": 600,
      "zones": {
        "Z1": 0,
        "Z2": 0,
        "Z3": 0,
        "Z4": 0,
        "Z5": 0
      },
      "last_7": {
        "Sat (12/20)": 0,
        "Sun (12/21)": 0,
        "Mon (12/22)": 0,
        "Tue (12/23)": 0,
        "Wed (12/24)": 0,
        "Thu (12/25)": 0,
        "Fri (12/26)": 0,
        "PTO remaining": 0
      },
      "sports": {}
    },
    {
      "name": "Darlene",
      "score": 665.3,
      "zones": {
        "Z1": 62.66999440522938,
        "Z2": 37.33000559477062,
        "Z3": 0.0,
        "Z4": 0.0,
        "Z5": 0.0
      },
      "last_7": {
        "Sat (12/20)": 0,
        "Sun (12/21)": 50,
        "Mon (12/22)": 0,
        "Tue (12/23)": 0,
        "Wed (12/24)": 0,
        "Thu (12/25)": 0,
        "Fri (12/26)": 0,
        "PTO remaining": 0
      },
      "sports": {
        "Workout": 4.0
      }
    },
    {
      "name": "Brad",
      "score": 842.3,
      "zones": {
        "Z1": 10.070080291866843,
        "Z2": 61.041175688166874,
        "Z3": 21.8949767858224,
        "Z4": 6.99376723414485,
        "Z5": 0.0
      },
      "last_7": {
        "Sat (12/20)": 44.0,
        "Sun (12/21)": 0,
        "Mon (12/22)": 48.3,
        "Tue (12/23)": 50,
        "Wed (12/24)": 50,
        "Thu (12/25)": 0,
        "Fri (12/26)": 0,
        "PTO remaining": 0
      },
      "sports": {
        "WeightTraining": 2.0,
        "Walk": 1.0,
        "Run": 3.0
      }
    },
    {
      "name": "Kevin",
      "score": 600,
      "zones": {
        "Z1": 0,
        "Z2": 0,
        "Z3": 0,
        "Z4": 0,
        "Z5": 0
      },
      "last_7": {
        "Sat (12/20)": 0,
        "Sun (12/21)": 0,
        "Mon (12/22)": 0,
        "Tue (12/23)": 0,
        "Wed (12/24)": 0,
        "Thu (12/25)": 0,
        "Fri (12/26)": 0,
        "PTO remaining": 0
      },
      "sports": {}
    }
  ]
}